planalytix_airflow-1.0.3.dist-info/licenses/LICENSE
planalytix_provider/__init__.py
planalytix_provider/example_dags/__init__.py
planalytix_provider/example_dags/example_planalytix_sync.py
planalytix_provider/hooks/__init__.py
planalytix_provider/hooks/planalytix.py
planalytix_provider/operators/__init__.py
planalytix_provider/operators/sync.py
planalytix_provider/sensors/__init__.py
planalytix_provider/sensors/sync.py
planalytix_provider/triggers/__init__.py
planalytix_airflow-1.0.3.dist-info/METADATA
planalytix_airflow-1.0.3.dist-info/WHEEL
planalytix_airflow-1.0.3.dist-info/entry_points.txt
planalytix_airflow-1.0.3.dist-info/top_level.txt
planalytix_airflow-1.0.3.dist-info/RECORD
