Metadata-Version: 2.4
Name: planalytix-airflow
Version: 1.0.3
Summary: Apache Airflow provider for Planalytix data integration platform
Home-page: https://github.com/planalytix/planalytix-airflow
Author: Planalytix
Author-email: Planalytix <support@planalytix.com>
License-Expression: Apache-2.0
Project-URL: Homepage, https://planalytix.com
Project-URL: Documentation, https://docs.planalytix.com/integrations/airflow
Project-URL: Repository, https://github.com/planalytix/planalytix-airflow
Project-URL: Issues, https://github.com/planalytix/planalytix-airflow/issues
Keywords: airflow,planalytix,etl,data-integration,orchestration
Classifier: Development Status :: 5 - Production/Stable
Classifier: Intended Audience :: Developers
Classifier: Operating System :: OS Independent
Classifier: Programming Language :: Python :: 3
Classifier: Programming Language :: Python :: 3.8
Classifier: Programming Language :: Python :: 3.9
Classifier: Programming Language :: Python :: 3.10
Classifier: Programming Language :: Python :: 3.11
Classifier: Programming Language :: Python :: 3.12
Classifier: Framework :: Apache Airflow
Classifier: Framework :: Apache Airflow :: Provider
Requires-Python: >=3.8
License-File: LICENSE
Requires-Dist: apache-airflow>=2.5.0
Requires-Dist: requests>=2.28.0
Provides-Extra: dev
Requires-Dist: pytest>=7.0.0; extra == "dev"
Requires-Dist: pytest-asyncio>=0.20.0; extra == "dev"
Requires-Dist: responses>=0.22.0; extra == "dev"
Requires-Dist: black>=23.0.0; extra == "dev"
Requires-Dist: isort>=5.12.0; extra == "dev"
Requires-Dist: mypy>=1.0.0; extra == "dev"
Dynamic: author
Dynamic: home-page
Dynamic: license-file
Dynamic: requires-python
